authbox_django_template/__init__.py
authbox_django_template/_version.py
authbox_django_template/bs_get_all_text.py
authbox_django_template/convert_to_django.py
authbox_django_template/main.py
authbox_django_template-1.0.4.dist-info/licenses/LICENSE
authbox_django_template-1.0.4.dist-info/METADATA
authbox_django_template-1.0.4.dist-info/WHEEL
authbox_django_template-1.0.4.dist-info/entry_points.txt
authbox_django_template-1.0.4.dist-info/top_level.txt
authbox_django_template-1.0.4.dist-info/RECORD
